fr_config/__init__.py
fr_config/constants.py
fr_config/exceptions.py
fr_config/interfaces.py
fr_config/tagging.py
fr_config/_internal/__init__.py
fr_config/_internal/core/__init__.py
fr_config/_internal/core/path.py
fr_config/_internal/core/resolver.py
fr_config/_internal/core/validate.py
fr_config/_internal/implementation/__init__.py
fr_config/_internal/implementation/base.py
fr_config/_internal/implementation/loader.py
fr_config/_internal/implementation/writer.py
fr_config/_internal/utils/__init__.py
fr_config/_internal/utils/logging.py
fr_config/_internal/utils/path.py
fr_config/_internal/utils/typing.py
fr_config-0.2.1.dist-info/licenses/LICENSE
fr_config-0.2.1.dist-info/licenses/LICENSES.txt
schema/fr_config.json
fr_config-0.2.1.dist-info/METADATA
fr_config-0.2.1.dist-info/WHEEL
fr_config-0.2.1.dist-info/top_level.txt
fr_config-0.2.1.dist-info/RECORD
