Metadata-Version: 2.4
Name: fr_config
Version: 0.2.1
Summary: Floating Rock cascading configuration resolver
Author-email: "alex.telford" <alex.telford@floating-rock.com>
License: MIT
Project-URL: Homepage, https://github.com/FloatingRockStudio/fr_config
Project-URL: Repository, https://github.com/FloatingRockStudio/fr_config.git
Classifier: Development Status :: 3 - Alpha
Classifier: Intended Audience :: Developers
Classifier: License :: OSI Approved :: MIT License
Classifier: Operating System :: OS Independent
Classifier: Programming Language :: Python :: 3
Classifier: Programming Language :: Python :: 3.7
Classifier: Programming Language :: Python :: 3.8
Classifier: Programming Language :: Python :: 3.9
Classifier: Programming Language :: Python :: 3.10
Classifier: Programming Language :: Python :: 3.11
Requires-Python: <4,>=3.7
License-File: LICENSE
License-File: LICENSES.txt
Requires-Dist: jsonschema<5,>=4.21.1
Requires-Dist: pyjson5<2,>=1.6
Provides-Extra: dev
Requires-Dist: pytest; extra == "dev"
Requires-Dist: pytest-cov; extra == "dev"
Dynamic: license-file
